bin/lcm-example
bin/lcm-gen
bin/lcm-logfilter
bin/lcm-logger
bin/lcm-logplayer
bin/lcm-sink
bin/lcm-source
bin/lcm-tester
include/lcm/eventlog.h
include/lcm/lcm-cpp-impl.hpp
include/lcm/lcm-cpp.hpp
include/lcm/lcm.h
include/lcm/lcm_c_namespace.h
include/lcm/lcm_coretypes.h
include/lcm/lcm_export.h
include/lcm/lcm_version.h
lcm/__init__.py
lcm/__init__.pyi
lcm/_lcm.so
lcm/py.typed
lcm.libs/libglib-2-67715b71.0.so.0.8400.4
lcm.libs/libintl-4a76853f.so.8.4.3
lcm.libs/libpcre2-8-4e09f26e.so.0.12.0
lib/liblcm.a
lib/liblcm.so
lib/liblcm.so.1
lib/liblcm.so.1.5.2
lib/lcm/cmake/lcmConfig.cmake
lib/lcm/cmake/lcmConfigVersion.cmake
lib/lcm/cmake/lcmTargets-release.cmake
lib/lcm/cmake/lcmTargets.cmake
lib/lcm/cmake/lcmUtilities.cmake
share/aclocal/lcm.m4
share/man/man1/lcm-example.1
share/man/man1/lcm-gen.1
share/man/man1/lcm-logger.1
share/man/man1/lcm-logplayer.1
share/man/man1/lcm-sink.1
share/man/man1/lcm-source.1
share/man/man1/lcm-tester.1
lcm-1.5.2.dist-info/METADATA
lcm-1.5.2.dist-info/WHEEL
lcm-1.5.2.dist-info/entry_points.txt
lcm-1.5.2.dist-info/RECORD
lcm-1.5.2.dist-info/licenses/AUTHORS
lcm-1.5.2.dist-info/licenses/COPYING
