Metadata-Version: 2.2
Name: lcm
Version: 1.5.2
Summary: Lightweight Communication and Marshalling
Classifier: Development Status :: 4 - Beta
Classifier: Topic :: Communications
Classifier: Framework :: Robot Framework
Requires-Python: >=3.7
Provides-Extra: test
Requires-Dist: pytest; extra == "test"
